nuitka_hatch2/__about__.py
nuitka_hatch2/__init__.py
nuitka_hatch2/hooks.py
nuitka_hatch2/plugin.py
nuitka_hatch2-0.1.2.dist-info/METADATA
nuitka_hatch2-0.1.2.dist-info/WHEEL
nuitka_hatch2-0.1.2.dist-info/entry_points.txt
nuitka_hatch2-0.1.2.dist-info/licenses/LICENSE.txt
nuitka_hatch2-0.1.2.dist-info/RECORD
